pydarm/__init__.py
pydarm/__main__.py
pydarm/_version.py
pydarm/actuation.py
pydarm/analog.py
pydarm/calcs.py
pydarm/darm.py
pydarm/digital.py
pydarm/fir.py
pydarm/firtools.py
pydarm/hwinj.py
pydarm/measurement.py
pydarm/model.py
pydarm/pcal.py
pydarm/plot.py
pydarm/regression_utils.py
pydarm/sensing.py
pydarm/uncertainty.py
pydarm/utils.py
pydarm/cmd/__init__.py
pydarm/cmd/_args.py
pydarm/cmd/_const.py
pydarm/cmd/_git.py
pydarm/cmd/_gpr.py
pydarm/cmd/_history.py
pydarm/cmd/_influx.py
pydarm/cmd/_log.py
pydarm/cmd/_mcmc.py
pydarm/cmd/_mset.py
pydarm/cmd/_pcalplot.py
pydarm/cmd/_report.py
pydarm/cmd/_uncertainty.py
pydarm/cmd/_util.py
pydarm/cmd/commit.py
pydarm/cmd/config.py
pydarm/cmd/env.py
pydarm/cmd/export.py
pydarm/cmd/gds.py
pydarm/cmd/ls.py
pydarm/cmd/measure.py
pydarm/cmd/model.py
pydarm/cmd/report.py
pydarm/cmd/show.py
pydarm/cmd/status.py
pydarm/cmd/uncertainty.py
pydarm/cmd/upload.py
pydarm-1.0.1.dist-info/licenses/LICENSE
pydarm-1.0.1.dist-info/METADATA
pydarm-1.0.1.dist-info/WHEEL
pydarm-1.0.1.dist-info/entry_points.txt
pydarm-1.0.1.dist-info/top_level.txt
pydarm-1.0.1.dist-info/RECORD
