Metadata-Version: 2.4
Name: pydarm
Version: 1.0.1
Summary: pyDARM modeling package for LIGO detector calibration
Author-email: Evan Goetz <evan.goetz@ligo.org>
License: GPL-3.0-or-later
Project-URL: Source Code, https://git.ligo.org/Calibration/pydarm
Project-URL: Bug Tracker, https://git.ligo.org/Calibration/pydarm/-/issues
Project-URL: Documentation, https://calibration.docs.ligo.org/pydarm
Classifier: Development Status :: 4 - Beta
Classifier: Intended Audience :: Science/Research
Classifier: License :: OSI Approved :: GNU General Public License v3 or later (GPLv3+)
Classifier: Natural Language :: English
Classifier: Operating System :: OS Independent
Classifier: Programming Language :: Python
Classifier: Programming Language :: Python :: 3
Classifier: Programming Language :: Python :: 3.8
Classifier: Programming Language :: Python :: 3.9
Classifier: Programming Language :: Python :: 3.10
Classifier: Programming Language :: Python :: 3.11
Classifier: Topic :: Scientific/Engineering :: Astronomy
Classifier: Topic :: Scientific/Engineering :: Physics
Requires-Python: >=3.8
License-File: LICENSE
Requires-Dist: h5py
Requires-Dist: matplotlib
Requires-Dist: numpy
Requires-Dist: scipy
Provides-Extra: measurement
Requires-Dist: dttxml; extra == "measurement"
Requires-Dist: emcee; extra == "measurement"
Requires-Dist: gpstime; extra == "measurement"
Requires-Dist: scikit-learn>=1.2.0; extra == "measurement"
Provides-Extra: uncertainty
Requires-Dist: gpflow; extra == "uncertainty"
Requires-Dist: gwpy; extra == "uncertainty"
Requires-Dist: ligo-scald; extra == "uncertainty"
Requires-Dist: numpy<1.25; extra == "uncertainty"
Requires-Dist: tensorflow==2.15.0; extra == "uncertainty"
Requires-Dist: tensorflow-probability==0.23.0; extra == "uncertainty"
Requires-Dist: tqdm; extra == "uncertainty"
Provides-Extra: cmd
Requires-Dist: corner; extra == "cmd"
Requires-Dist: gitpython; extra == "cmd"
Requires-Dist: gpstime; extra == "cmd"
Requires-Dist: pyepics; extra == "cmd"
Requires-Dist: pydarm[measurement]; extra == "cmd"
Requires-Dist: pydarm[uncertainty]; extra == "cmd"
Requires-Dist: yaml; extra == "cmd"
Provides-Extra: test
Requires-Dist: flake8; extra == "test"
Requires-Dist: pytest; extra == "test"
Requires-Dist: pytest-cov; extra == "test"
Requires-Dist: pytest-xdist; extra == "test"
Requires-Dist: pydarm[cmd]; extra == "test"
Provides-Extra: docs
Requires-Dist: sphinx; extra == "docs"
Requires-Dist: sphinx-immaterial-igwn; extra == "docs"
Requires-Dist: numpydoc; extra == "docs"
Dynamic: license-file
